MIMICSectionizer/__init__.py
MIMICSectionizer/diagnoses_icd.csv.gz
MIMICSectionizer/icd_cohort_combined_searching.py
MIMICSectionizer/mimiciv_text_sectionizer.py
MIMICSectionizer/notes_embedding.py
mimicsectionizer-0.1.dist-info/METADATA
mimicsectionizer-0.1.dist-info/WHEEL
mimicsectionizer-0.1.dist-info/top_level.txt
mimicsectionizer-0.1.dist-info/RECORD
