Metadata-Version: 2.4
Name: MIMICSectionizer
Version: 0.1
Summary: Text Sectionizer and Text Embedding for MIMIC-IV-Notes.
